Metadata-Version: 1.1
Name: dictsheet
Version: 0.0.11
Summary: Dict wrapper for google spreadsheet
Home-page: https://github.com/previa/dictsheet
Author: Chandler Huang, Xander Li
Author-email: previa@gmail.com
License: MIT License
Keywords: dictsheet,spreadsheet,gspread
Platform: any
Classifier: Programming Language :: Python :: 2.6
Classifier: Programming Language :: Python :: 2.7
Classifier: Programming Language :: Python :: 3.0
Classifier: Programming Language :: Python :: 3.1
Classifier: Programming Language :: Python :: 3.2
Classifier: Programming Language :: Python :: 3.3
Classifier: Programming Language :: Python :: 3.4
Classifier: Programming Language :: Python :: 3.5
